full_width/__init__.py
full_width/full_width.py
full_width-1.0.1.dist-info/METADATA
full_width-1.0.1.dist-info/WHEEL
full_width-1.0.1.dist-info/entry_points.txt
full_width-1.0.1.dist-info/licenses/LICENSE
full_width-1.0.1.dist-info/RECORD
