Metadata-Version: 2.3
Name: full-width
Version: 1.0.1
Summary: Half-width to full-width character converter.
Project-URL: Homepage, https://github.com/mizu-hikaru/full-width
Project-URL: Issues, https://github.com/mizu-hikaru/full-width/issues
Author-email: Mizu Hikaru <mizu@hikaru.org>
License-File: LICENSE
Classifier: License :: OSI Approved :: MIT License
Classifier: Operating System :: OS Independent
Classifier: Programming Language :: Python :: 3
Requires-Python: >=3.9
